firefin/__init__.py
firefin/cli/command.py
firefin/common/config.py
firefin/common/config.yaml
firefin/common/const.py
firefin/compute/__init__.py
firefin/compute/window.py
firefin/core/__init__.py
firefin/core/algorithm/MSR_Test.py
firefin/core/algorithm/__init__.py
firefin/core/algorithm/_numba_funcs.py
firefin/core/algorithm/anomaly_test.py
firefin/core/algorithm/cross_sectional_regression.py
firefin/core/algorithm/fama_macbeth.py
firefin/core/algorithm/grs.py
firefin/core/algorithm/newey_west_t_statistics.py
firefin/core/algorithm/newey_west_ttest_1samp.py
firefin/core/algorithm/portfolio_sort.py
firefin/core/algorithm/regression.py
firefin/core/algorithm/winsorizer.py
firefin/core/eva_utils.py
firefin/core/plot/__init__.py
firefin/core/plot/plots.py
firefin/core/plot/table_and_latex_code.py
firefin/data/__init__.py
firefin/data/datainfo.py
firefin/data/fake.py
firefin/data/file_reader.py
firefin/data/gateway.py
firefin/evaluation/__init__.py
firefin/evaluation/academia/AcaEvaluatorModel.py
firefin/evaluation/academia/AcaEvaluatorModelComparison.py
firefin/evaluation/academia/AcaIndirectEvaluator.py
firefin/evaluation/academia/AcademicFactors.py
firefin/evaluation/academia/__init__.py
firefin/evaluation/industry/__init__.py
firefin/evaluation/industry/evaluator.py
firefin-0.3.2.dist-info/WHEEL
firefin-0.3.2.dist-info/entry_points.txt
firefin-0.3.2.dist-info/METADATA
firefin-0.3.2.dist-info/RECORD
