Metadata-Version: 2.3
Name: firefin
Version: 0.3.2
Summary: The bundled opensource toolkit for book Navigate through the Factor Zoo: The Science of Factor Investing.
Author: Renjie Liao, Baochen Qiao
Author-email: Renjie Liao <auderson@qq.com>, Baochen Qiao <baochenqiao@gmail.com>
Requires-Dist: click>=8.1.3
Requires-Dist: pandas>=2.2.1
Requires-Dist: matplotlib>=3.8.3
Requires-Dist: seaborn>=0.13.2
Requires-Dist: statsmodels>=0.14.1
Requires-Dist: scipy>=1.12.0
Requires-Dist: numba>=0.59.0
Requires-Dist: loguru>=0.7.2
Requires-Dist: tqdm>=4.66.4
Requires-Dist: joblib>=1.4.2
